testasad/__init__.py
testasad/testasad.py
testasad-0.1.dist-info/DESCRIPTION.rst
testasad-0.1.dist-info/METADATA
testasad-0.1.dist-info/RECORD
testasad-0.1.dist-info/WHEEL
testasad-0.1.dist-info/metadata.json
testasad-0.1.dist-info/top_level.txt
