Metadata-Version: 2.0
Name: testasad
Version: 0.1
Summary: Datorama Python Package
Home-page: https://github.com/datorama/python-connector-package
Author: Asaad Awesat
Author-email: asaad.awesat@datorama.com
License: MIT
Platform: UNKNOWN
